resumableds/__init__.py
resumableds/__version__.py
resumableds/featherfs.py
resumableds/fs.py
resumableds/functimelog.py
resumableds/hasher.py
resumableds/logger.py
resumableds/parquetfs.py
resumableds/plotfs.py
resumableds/project.py
resumableds-1.0.0.dist-info/LICENSE
resumableds-1.0.0.dist-info/METADATA
resumableds-1.0.0.dist-info/WHEEL
resumableds-1.0.0.dist-info/top_level.txt
resumableds-1.0.0.dist-info/zip-safe
resumableds-1.0.0.dist-info/RECORD
