Metadata-Version: 2.1
Name: resumableds
Version: 1.0.0
Summary: A Python class that supports Data Science projects.
Home-page: https://github.com/systemverwalter/resumableds
Author: David Riedel
Author-email: systemverwalter@gmail.com
Classifier: Development Status :: 5 - Production/Stable
Classifier: Programming Language :: Python :: 3
Classifier: License :: OSI Approved :: MIT License
Classifier: Operating System :: OS Independent
Classifier: Framework :: Jupyter
Classifier: Intended Audience :: Information Technology
Classifier: Intended Audience :: Science/Research
Classifier: Topic :: Scientific/Engineering :: Information Analysis
Classifier: Topic :: Utilities
License-File: LICENSE
Requires-Dist: pandas
Requires-Dist: pyyaml
